[
  {
    "id": "platform-instagram-check",
    "name": "📸 Has Instagram Content?",
    "type": "if",
    "parameters": {
      "conditions": {
        "boolean": [
          {
            "value1": "={{ $json.instagram !== undefined }}",
            "value2": true
          }
        ]
      }
    },
    "position": [200, 0],
    "typeVersion": 2
  },
  {
    "id": "platform-instagram-post",
    "name": "📸 Post to Instagram",
    "type": "instagram",
    "parameters": {
      "operation": "createPost",
      "additionalFields": {}
    },
    "position": [400, 0],
    "typeVersion": 1
  },
  {
    "id": "platform-instagram-emit-started",
    "name": "📡 Emit Instagram Started",
    "type": "httpRequest",
    "parameters": {
      "method": "POST",
      "url": "={{ $json.callbackUrl || $json.metadata?.callbackUrl || 'http://localhost:3000/api/publish/event' }}",
      "sendBody": true,
      "specifyBody": "json",
      "jsonBody": "={{ { sessionId: $json.sessionId || $json.metadata?.sessionId || $json.metadata?.eventData?.sessionId, publishRunId: $json.publishRunId || $json.metadata?.publishRunId || $json.metadata?.eventData?.publishRunId, type: 'step_started', platform: 'instagram', method: 'n8n', step: 'publish.submit', message: 'Starting publish.submit via n8n', timestamp: $now.toISO() } }}",
      "options": {}
    },
    "position": [300, -60],
    "typeVersion": 4.2
  },
  {
    "id": "platform-instagram-emit-completed",
    "name": "✅ Emit Instagram Completed",
    "type": "httpRequest",
    "parameters": {
      "method": "POST",
      "url": "={{ $json.callbackUrl || $json.metadata?.callbackUrl || 'http://localhost:3000/api/publish/event' }}",
      "sendBody": true,
      "specifyBody": "json",
      "jsonBody": "={{ { sessionId: $json.sessionId || $json.metadata?.sessionId || $json.metadata?.eventData?.sessionId, publishRunId: $json.publishRunId || $json.metadata?.publishRunId || $json.metadata?.eventData?.publishRunId, type: 'step_completed', platform: 'instagram', method: 'n8n', step: 'publish.submit', duration: 0, data: { postId: $json.id || $json.media_id, url: $json.url || $json.permalink }, timestamp: $now.toISO() } }}",
      "options": {}
    },
    "position": [520, 0],
    "typeVersion": 4.2
  }
]
